appsync_function_uploader/__init__.py
appsync_function_uploader/__main__.py
appsync_function_uploader-0.0.5.dist-info/LICENSE
appsync_function_uploader-0.0.5.dist-info/METADATA
appsync_function_uploader-0.0.5.dist-info/WHEEL
appsync_function_uploader-0.0.5.dist-info/top_level.txt
appsync_function_uploader-0.0.5.dist-info/RECORD
