Metadata-Version: 2.1
Name: appsync-function-uploader
Version: 0.0.5
Summary: Creates or updates an AWS AppSync function
Home-page: https://github.com/QuiNovas/appsync-function-uploader
Author: Joseph Wortmann
Author-email: joseph.wortmann@gmail.com
License: APL 2.0
Keywords: quinovas
Platform: UNKNOWN
Classifier: Development Status :: 3 - Alpha
Classifier: Topic :: System :: Software Distribution
Classifier: Intended Audience :: Developers
Classifier: License :: OSI Approved :: Apache Software License
Classifier: Programming Language :: Python :: 2.7
Requires-Dist: argparse
Requires-Dist: boto3 (>=1.9.156)
